[
  {
    "databaseName": "ms",
    "apiName": "User",
    "apiZHName": "用户",
    "apiDesc": "用户信息接口",
    "collectionName": "user"
  },
  {
    "databaseName": "ms",
    "apiName": "Movie",
    "apiZHName": "电影",
    "apiDesc": "电影的增删改查接口",
    "collectionName": "movie"
  },
  {
    "databaseName": "ms",
    "apiName": "MovieTags",
    "apiZHName": "电影标签",
    "apiDesc": "对电影进行标签分类",
    "collectionName": "movietags"
  },
  {
    "databaseName": "ms",
    "apiName": "MovieFavorite",
    "apiZHName": "喜欢的电影",
    "apiDesc": "用户喜欢的电影",
    "collectionName": "moviefavorite"
  },
  {
    "databaseName": "ms",
    "apiName": "MovieTypes",
    "apiZHName": "电影类型",
    "apiDesc": "电影大类",
    "collectionName": "movietypes"
  },
  {
    "databaseName": "ms",
    "apiName": "MoviePlatforms",
    "apiZHName": "电影平台",
    "apiDesc": "电影平台",
    "collectionName": "movieplatforms"
  },
  {
    "databaseName": "ms",
    "apiName": "MovieStarrings",
    "apiZHName": "电影明星",
    "apiDesc": "电影明星信息接口",
    "collectionName": "moviestarrings"
  },
  {
    "databaseName": "ms",
    "apiName": "Music",
    "apiZHName": "音乐",
    "apiDesc": "音乐接口",
    "collectionName": "music"
  },
  {
    "databaseName": "ms",
    "apiName": "MusicFavorite",
    "apiZHName": "喜欢的音乐",
    "apiDesc": "喜欢的音乐",
    "collectionName": "musicfavorite"
  },
  {
    "databaseName": "ms",
    "apiName": "Image",
    "apiZHName": "图片",
    "apiDesc": "图片",
    "collectionName": "image"
  },
  {
    "databaseName": "ms",
    "apiName": "MovieDirects",
    "apiZHName": "电影目录",
    "apiDesc": "电影目录",
    "collectionName": "moviedirects"
  },
  {
    "databaseName": "ms",
    "apiName": "Role",
    "apiZHName": "角色",
    "apiDesc": "角色",
    "collectionName": "role"
  },
  {
    "databaseName": "ms",
    "apiName": "RoleBtns",
    "apiZHName": "角色按钮权限",
    "apiDesc": "角色按钮权限",
    "collectionName": "rolebtns"
  },
  {
    "databaseName": "ms",
    "apiName": "RoleMenus",
    "apiZHName": "角色菜单",
    "apiDesc": "角色菜单",
    "collectionName": "rolemenus"
  },
  {
    "databaseName": "ms",
    "apiName": "Menu",
    "apiZHName": "菜单",
    "apiDesc": "菜单",
    "collectionName": "menu"
  },
  {
    "databaseName": "ms",
    "apiName": "Source",
    "apiZHName": "资源",
    "apiDesc": "资源",
    "collectionName": "source"
  },
  {
    "databaseName": "ms",
    "apiName": "Route",
    "apiZHName": "路由",
    "apiDesc": "路由",
    "collectionName": "route"
  }
]